price_watcher/__init__.py
price_watcher/__main__.py
price_watcher/amazon.py
price_watcher/cli.py
price_watcher/notifications.py
price_watcher/thistle_and_spire.py
price_watcher-2.0.0.dist-info/LICENSE
price_watcher-2.0.0.dist-info/METADATA
price_watcher-2.0.0.dist-info/WHEEL
price_watcher-2.0.0.dist-info/entry_points.txt
price_watcher-2.0.0.dist-info/top_level.txt
price_watcher-2.0.0.dist-info/RECORD
