Metadata-Version: 2.1
Name: price-watcher
Version: 2.0.0
Summary: Watches prices on amazon product pages
Home-page: https://github.com/bachmann1234/price_watcher
Author: Matt Bachmann
Author-email: bachmann.matt@gmail.com
License: Apache 2.0
Platform: UNKNOWN
Classifier: License :: OSI Approved :: Apache Software License
Classifier: Programming Language :: Python
Classifier: Programming Language :: Python :: 3
Classifier: Programming Language :: Python :: 3.9
Classifier: Programming Language :: Python :: Implementation :: CPython
Classifier: Programming Language :: Python :: Implementation :: PyPy
Requires-Python: >=3.9.0
License-File: LICENSE
Requires-Dist: requests
Requires-Dist: Click
Requires-Dist: beautifulsoup4
Requires-Dist: twilio
